zappa_layer/__init__.py
zappa_layer/layer_manage.py
zappa_layer-0.1.2.dist-info/METADATA
zappa_layer-0.1.2.dist-info/WHEEL
zappa_layer-0.1.2.dist-info/entry_points.txt
zappa_layer-0.1.2.dist-info/top_level.txt
zappa_layer-0.1.2.dist-info/RECORD
